README.rst
ez_setup.py
install.bat
setup.py
ErepMessenger.egg-info/PKG-INFO
ErepMessenger.egg-info/SOURCES.txt
ErepMessenger.egg-info/dependency_links.txt
ErepMessenger.egg-info/requires.txt
ErepMessenger.egg-info/top_level.txt
erepmessenger/__init__.py
erepmessenger/config.cfg
erepmessenger/messenger.gif
erepmessenger/messenger.ico
erepmessenger/messenger.pyw