Metadata-Version: 1.0
Name: ErepMessenger
Version: 0.9.4.4
Summary: App to send mass in game messages for Erepublik
Home-page: https://pypi.python.org/pypi/ErepMessenger
Author: Mike Ontry
Author-email: mr.ontry@gmail.com
License: PSF
Keywords: erepublik mass messaging
Platform: UNKNOWN
